.gitignore
LICENSE.txt
MANIFEST.in
NOTICE.txt
README.rst
build-dist.sh
setup.py
tox.ini
disdat_luigi.egg-info/PKG-INFO
disdat_luigi.egg-info/SOURCES.txt
disdat_luigi.egg-info/dependency_links.txt
disdat_luigi.egg-info/entry_points.txt
disdat_luigi.egg-info/requires.txt
disdat_luigi.egg-info/top_level.txt
disdatluigi/.gitignore
disdatluigi/VERSION
disdatluigi/__init__.py
disdatluigi/api.py
disdatluigi/apply.py
disdatluigi/cli_extension.py
disdatluigi/common.py
disdatluigi/dockerize.py
disdatluigi/log.py
disdatluigi/pipe.py
disdatluigi/pipe_base.py
disdatluigi/resource.py
disdatluigi/run.py
disdatluigi/version.py
disdatluigi/config/README.md
disdatluigi/config/__init__.py
disdatluigi/config/disdatluigi/.exclude-from-modeler-docker-image
disdatluigi/config/disdatluigi/disdatluigi.cfg
disdatluigi/config/disdatluigi/luigi.cfg
disdatluigi/entrypoints/__init__.py
disdatluigi/entrypoints/docker_ep.py
disdatluigi/entrypoints/sagemaker_ep.py
disdatluigi/infrastructure/.gitignore
disdatluigi/infrastructure/README.md
disdatluigi/infrastructure/__init__.py
disdatluigi/infrastructure/dockerizer/Makefile
disdatluigi/infrastructure/dockerizer/__init__.py
disdatluigi/infrastructure/dockerizer/config.mk.template
disdatluigi/infrastructure/dockerizer/setup_tools_commands.py
disdatluigi/infrastructure/dockerizer/config/.gitignore
disdatluigi/infrastructure/dockerizer/context.template/.dockerignore
disdatluigi/infrastructure/dockerizer/context.template/Dockerfiles/00-disdat-python-3.11-slim.dockerfile
disdatluigi/infrastructure/dockerizer/context.template/Dockerfiles/00-disdat-ubuntu-14.04.dockerfile
disdatluigi/infrastructure/dockerizer/context.template/Dockerfiles/00-disdat-ubuntu-16.04.dockerfile
disdatluigi/infrastructure/dockerizer/context.template/Dockerfiles/01-disdat-python.dockerfile
disdatluigi/infrastructure/dockerizer/context.template/Dockerfiles/02-user.dockerfile
disdatluigi/infrastructure/dockerizer/context.template/Dockerfiles/03-sagemaker.dockerfile
disdatluigi/infrastructure/dockerizer/context.template/kickstart/bin/find_packages_from_setup.py
disdatluigi/infrastructure/dockerizer/context.template/kickstart/bin/install-python-package-from-source-tree.sh
