Metadata-Version: 2.4
Name: disdat-luigi
Version: 1.0.2
Summary: Disdat-Luigi: Data-versioned Luigi Workflows
Home-page: https://github.com/kyocum/disdat-luigi
Author: Ken Yocum
Author-email: kyocum@gmail.com
License: Apache License, version 2.0
Classifier: Development Status :: 5 - Production/Stable
Classifier: Intended Audience :: Science/Research
Classifier: Topic :: Scientific/Engineering
Classifier: License :: OSI Approved :: Apache Software License
Classifier: Programming Language :: Python :: 3.9
Classifier: Programming Language :: Python :: 3.10
Classifier: Programming Language :: Python :: 3.11
Classifier: Programming Language :: Python :: 3.12
Classifier: Programming Language :: Python :: 3.13
Classifier: Operating System :: OS Independent
Classifier: Natural Language :: English
License-File: LICENSE.txt
License-File: NOTICE.txt
Requires-Dist: disdat>=1.1.3
Requires-Dist: luigi<3.6,>=3.0
Requires-Dist: boto3<2.0,>=1.14.49
Requires-Dist: docker<7.2.0,>=7.0.0
Provides-Extra: dev
Requires-Dist: pytest; extra == "dev"
Requires-Dist: ipython; extra == "dev"
Requires-Dist: mock; extra == "dev"
Requires-Dist: pylint; extra == "dev"
Requires-Dist: coverage; extra == "dev"
Requires-Dist: tox; extra == "dev"
Requires-Dist: moto>=5; extra == "dev"
Requires-Dist: fastparquet; extra == "dev"
Requires-Dist: s3fs<=0.4.2; extra == "dev"
Provides-Extra: rel
Requires-Dist: wheel; extra == "rel"
Dynamic: author
Dynamic: author-email
Dynamic: classifier
Dynamic: home-page
Dynamic: license
Dynamic: license-file
Dynamic: provides-extra
Dynamic: requires-dist
Dynamic: summary
